datasdk/__about__.py
datasdk/__init__.py
datasdk/py.typed
datasdk-0.0.1.dist-info/METADATA
datasdk-0.0.1.dist-info/WHEEL
datasdk-0.0.1.dist-info/licenses/LICENSE.txt
datasdk-0.0.1.dist-info/RECORD
