Metadata-Version: 2.1
Name: datasdk
Version: 0.0.1
Project-URL: Documentation, https://github.com/nuxion/datasdk#readme
Project-URL: Issues, https://github.com/nuxion/datasdk/issues
Project-URL: Source, https://github.com/nuxion/datasdk
Author-email: Xavier Petit <nuxion@gmail.com>
License-Expression: MIT
License-File: LICENSE.txt
Classifier: Development Status :: 4 - Beta
Classifier: Programming Language :: Python
Classifier: Programming Language :: Python :: 3.7
Classifier: Programming Language :: Python :: 3.8
Classifier: Programming Language :: Python :: 3.9
Classifier: Programming Language :: Python :: 3.10
Classifier: Programming Language :: Python :: 3.11
Classifier: Programming Language :: Python :: Implementation :: CPython
Classifier: Programming Language :: Python :: Implementation :: PyPy
Requires-Python: >=3.7
Provides-Extra: jupyter
Requires-Dist: jupyterlab~=3.6.2; extra == 'jupyter'
Requires-Dist: jupytext~=1.14.5; extra == 'jupyter'
